WebGrab/__init__.py
WebGrab/base_scary.py
WebGrab/httpbin.py
WebGrab/jiangxianli.py
WebGrab/resolu.py
web-grab/__init__.py
web-grab/base_scary.py
web-grab/httpbin.py
web-grab/jiangxianli.py
web-grab/resolu.py
web_grab/__init__.py
web_grab/base_scary.py
web_grab/httpbin.py
web_grab/jiangxianli.py
web_grab/resolu.py
WebGrab-0.1.dist-info/LICENSE
WebGrab-0.1.dist-info/METADATA
WebGrab-0.1.dist-info/WHEEL
WebGrab-0.1.dist-info/top_level.txt
WebGrab-0.1.dist-info/RECORD
