Metadata-Version: 2.1
Name: WebGrab
Version: 0.1
Summary: 
Home-page: https://gitee.com/ntshibin/grab.git
Author: bineanshi
Author-email: bineanshi@sina.com
License: UNKNOWN
Platform: UNKNOWN
Classifier: Programming Language :: Python :: 3
Classifier: License :: OSI Approved :: MIT License
Classifier: Operating System :: OS Independent
License-File: LICENSE
Requires-Dist: lxml (==4.6.3)
Requires-Dist: requests (==2.26.0)
